<?xml version="1.0" encoding="windows-1251"?>

<!--
	Weapons Attachments
-->

<string_table>

	<string id="st_addon_sil_762nato">
		<text>KAC QDC 7.62x51 NATO Silencer</text>
	</string>
	<string id="st_addon_scope_descr">
		<text>\n \n%c[ui_gray_2]COMPATIBILITY:\n \n%c[d_cyan] • %c[ui_gray_2] most 7.62x51 NATO rifles\n \n%c[ui_gray_1]A modern 7.62x51 NATO silencer. Currently employed by various SOF and Law Enforcement agencies, and feature an innovative mounting method, providing effective flash and sound suppression.\n \n
		%c[d_purple] • %c[ui_gray_2] Condition: %c[ui_gray_1]good\n
		</text>
	</string>
	
</string_table>
